async_payok/__init__.py
async_payok/__version__.py
async_payok/asyncpayok.py
async_payok/exceptions.py
async_payok/models/__init__.py
async_payok/models/balance.py
async_payok/models/enums.py
async_payok/models/invoice.py
async_payok/models/methods.py
async_payok-0.3.0.dist-info/METADATA
async_payok-0.3.0.dist-info/WHEEL
async_payok-0.3.0.dist-info/top_level.txt
async_payok-0.3.0.dist-info/RECORD
